yadict/__init__.py
yadict/client.py
yadict-0.1.1.dist-info/METADATA
yadict-0.1.1.dist-info/WHEEL
yadict-0.1.1.dist-info/top_level.txt
yadict-0.1.1.dist-info/RECORD
