Metadata-Version: 2.1
Name: yadict
Version: 0.1.1
Summary: Client for Yandex Dictionary API
Author-email: Ivan Slepovichev <gurgutan@yandex.ru>
License: MIT
Requires-Python: >=3.10
Requires-Dist: requests
